[
    {
        "index": 1,
        "title": "«Что может Python на микроконтроллерах» Андрей Власовских, JetBrains",
        "url": "https://www.youtube.com/watch?v=vmUdCI1iZ3U",
        "video_id": "vmUdCI1iZ3U",
        "uploader": "Видео с мероприятий {speach!",
        "uploader_id": "@videospeach",
        "uploader_url": "https://www.youtube.com/@videospeach",
        "upload_date": "20170814",
        "duration": 1996,
        "view_count": 32805,
        "like_count": 1032,
        "comment_count": 99,
        "tags": [
            "python",
            "pycon"
        ],
        "categories": [
            "Education"
        ],
        "description": "Выступление на конференции PyCon Russia 2017",
        "thumbnail": "https://i.ytimg.com/vi_webp/vmUdCI1iZ3U/maxresdefault.webp",
        "age_limit": 0,
        "is_live": false,
        "was_live": false,
        "availability": "public",
        "webpage_url": "https://www.youtube.com/watch?v=vmUdCI1iZ3U",
        "original_url": "https://www.youtube.com/watch?v=vmUdCI1iZ3U"
    },
    {
        "index": 2,
        "title": "«Python of Things» Кирилл Борисов, Яндекс",
        "url": "https://www.youtube.com/watch?v=w2WPk2P04BM",
        "video_id": "w2WPk2P04BM",
        "uploader": "Видео с мероприятий {speach!",
        "uploader_id": "@videospeach",
        "uploader_url": "https://www.youtube.com/@videospeach",
        "upload_date": "20170814",
        "duration": 2320,
        "view_count": 5764,
        "like_count": 176,
        "comment_count": 4,
        "tags": [
            "python",
            "pycon"
        ],
        "categories": [
            "Education"
        ],
        "description": "Выступление на конференции PYCON RUSSIA 2017",
        "thumbnail": "https://i.ytimg.com/vi_webp/w2WPk2P04BM/maxresdefault.webp",
        "age_limit": 0,
        "is_live": false,
        "was_live": false,
        "availability": "public",
        "webpage_url": "https://www.youtube.com/watch?v=w2WPk2P04BM",
        "original_url": "https://www.youtube.com/watch?v=w2WPk2P04BM"
    },
    {
        "index": 3,
        "title": "«Why is Python slow?» Maciej Fijałkowski, PyPy",
        "url": "https://www.youtube.com/watch?v=NNgylFbNH8I",
        "video_id": "NNgylFbNH8I",
        "uploader": "Видео с мероприятий {speach!",
        "uploader_id": "@videospeach",
        "uploader_url": "https://www.youtube.com/@videospeach",
        "upload_date": "20170814",
        "duration": 1888,
        "view_count": 1672,
        "like_count": 25,
        "comment_count": null,
        "tags": [
            "python",
            "pycon"
        ],
        "categories": [
            "Education"
        ],
        "description": "Выступление на конференции PYCON RUSSIA 2017",
        "thumbnail": "https://i.ytimg.com/vi_webp/NNgylFbNH8I/maxresdefault.webp",
        "age_limit": 0,
        "is_live": false,
        "was_live": false,
        "availability": "public",
        "webpage_url": "https://www.youtube.com/watch?v=NNgylFbNH8I",
        "original_url": "https://www.youtube.com/watch?v=NNgylFbNH8I"
    },
    {
        "index": 4,
        "title": "«Память и Python. Что надо знать для счастья?» Алексей Кузьмин, ЦНС",
        "url": "https://www.youtube.com/watch?v=D0vbuIDOV4c",
        "video_id": "D0vbuIDOV4c",
        "uploader": "Видео с мероприятий {speach!",
        "uploader_id": "@videospeach",
        "uploader_url": "https://www.youtube.com/@videospeach",
        "upload_date": "20170814",
        "duration": 1851,
        "view_count": 66500,
        "like_count": 3411,
        "comment_count": 65,
        "tags": [
            "python",
            "pycon"
        ],
        "categories": [
            "Education"
        ],
        "description": "Выступление на конференции PYCON RUSSIA 2017",
        "thumbnail": "https://i.ytimg.com/vi/D0vbuIDOV4c/hqdefault.jpg?sqp=-oaymwEmCOADEOgC8quKqQMa8AEB-AH-CYAC0AWKAgwIABABGDYgXChyMA8=&rs=AOn4CLBAjDFRyw5zAiMw7nraP2bF_52rPg",
        "age_limit": 0,
        "is_live": false,
        "was_live": false,
        "availability": "public",
        "webpage_url": "https://www.youtube.com/watch?v=D0vbuIDOV4c",
        "original_url": "https://www.youtube.com/watch?v=D0vbuIDOV4c"
    },
    {
        "index": 5,
        "title": "«Python на острие бритвы: PyPy project» Александр Кошкин, Positive Technologies",
        "url": "https://www.youtube.com/watch?v=a4M5nsO6ofk",
        "video_id": "a4M5nsO6ofk",
        "uploader": "Видео с мероприятий {speach!",
        "uploader_id": "@videospeach",
        "uploader_url": "https://www.youtube.com/@videospeach",
        "upload_date": "20170814",
        "duration": 2063,
        "view_count": 2164,
        "like_count": 19,
        "comment_count": 6,
        "tags": [
            "python",
            "pycon"
        ],
        "categories": [
            "Education"
        ],
        "description": "Выступление на конференции PYCON RUSSIA 2017",
        "thumbnail": "https://i.ytimg.com/vi_webp/a4M5nsO6ofk/maxresdefault.webp",
        "age_limit": 0,
        "is_live": false,
        "was_live": false,
        "availability": "public",
        "webpage_url": "https://www.youtube.com/watch?v=a4M5nsO6ofk",
        "original_url": "https://www.youtube.com/watch?v=a4M5nsO6ofk"
    },
    {
        "index": 6,
        "title": "«Детские болезни live-чата» Ольга Сентемова, Тинькофф Банк",
        "url": "https://www.youtube.com/watch?v=x10KoA0won0",
        "video_id": "x10KoA0won0",
        "uploader": "Видео с мероприятий {speach!",
        "uploader_id": "@videospeach",
        "uploader_url": "https://www.youtube.com/@videospeach",
        "upload_date": "20170814",
        "duration": 1706,
        "view_count": 950,
        "like_count": 11,
        "comment_count": 2,
        "tags": [
            "python",
            "pycon"
        ],
        "categories": [
            "Education"
        ],
        "description": "Выступление на конференции PYCON RUSSIA 2017",
        "thumbnail": "https://i.ytimg.com/vi_webp/x10KoA0won0/maxresdefault.webp",
        "age_limit": 0,
        "is_live": false,
        "was_live": false,
        "availability": "public",
        "webpage_url": "https://www.youtube.com/watch?v=x10KoA0won0",
        "original_url": "https://www.youtube.com/watch?v=x10KoA0won0"
    },
    {
        "index": 7,
        "title": "«Что такое serverless-архитектура и как с ней жить?» Николай Марков, Aligned Research Group",
        "url": "https://www.youtube.com/watch?v=Hs9Xbu9236I",
        "video_id": "Hs9Xbu9236I",
        "uploader": "Видео с мероприятий {speach!",
        "uploader_id": "@videospeach",
        "uploader_url": "https://www.youtube.com/@videospeach",
        "upload_date": "20170814",
        "duration": 1963,
        "view_count": 4668,
        "like_count": 81,
        "comment_count": 5,
        "tags": [
            "python",
            "pycon"
        ],
        "categories": [
            "Education"
        ],
        "description": "Выступление на конференции PYCON RUSSIA 2017",
        "thumbnail": "https://i.ytimg.com/vi/Hs9Xbu9236I/hqdefault.jpg",
        "age_limit": 0,
        "is_live": false,
        "was_live": false,
        "availability": "public",
        "webpage_url": "https://www.youtube.com/watch?v=Hs9Xbu9236I",
        "original_url": "https://www.youtube.com/watch?v=Hs9Xbu9236I"
    },
    {
        "index": 8,
        "title": "«(Без)опасный Python» Иван Цыганов, Positive Technologies",
        "url": "https://www.youtube.com/watch?v=lbkuNYWIgbA",
        "video_id": "lbkuNYWIgbA",
        "uploader": "Видео с мероприятий {speach!",
        "uploader_id": "@videospeach",
        "uploader_url": "https://www.youtube.com/@videospeach",
        "upload_date": "20170814",
        "duration": 2509,
        "view_count": 4361,
        "like_count": 177,
        "comment_count": 1,
        "tags": [
            "python",
            "pycon"
        ],
        "categories": [
            "Education"
        ],
        "description": "Выступление на конференции PYCON RUSSIA 2017",
        "thumbnail": "https://i.ytimg.com/vi/lbkuNYWIgbA/hqdefault.jpg",
        "age_limit": 0,
        "is_live": false,
        "was_live": false,
        "availability": "public",
        "webpage_url": "https://www.youtube.com/watch?v=lbkuNYWIgbA",
        "original_url": "https://www.youtube.com/watch?v=lbkuNYWIgbA"
    },
    {
        "index": 9,
        "title": "«Микросервисы наносят ответный удар!» Олег Чуркин, Rambler&Co",
        "url": "https://www.youtube.com/watch?v=_ybFAv3oUkU",
        "video_id": "_ybFAv3oUkU",
        "uploader": "Видео с мероприятий {speach!",
        "uploader_id": "@videospeach",
        "uploader_url": "https://www.youtube.com/@videospeach",
        "upload_date": "20170814",
        "duration": 3229,
        "view_count": 2625,
        "like_count": 70,
        "comment_count": null,
        "tags": [
            "python",
            "pycon"
        ],
        "categories": [
            "Education"
        ],
        "description": "Выступление на конференции PYCON RUSSIA 2017",
        "thumbnail": "https://i.ytimg.com/vi_webp/_ybFAv3oUkU/maxresdefault.webp",
        "age_limit": 0,
        "is_live": false,
        "was_live": false,
        "availability": "public",
        "webpage_url": "https://www.youtube.com/watch?v=_ybFAv3oUkU",
        "original_url": "https://www.youtube.com/watch?v=_ybFAv3oUkU"
    },
    {
        "index": 10,
        "title": "«PyWat. А хорошо ли вы знаете Python?» Александр Швец, Marilyn System",
        "url": "https://www.youtube.com/watch?v=Mhj8vqVUEhU",
        "video_id": "Mhj8vqVUEhU",
        "uploader": "Видео с мероприятий {speach!",
        "uploader_id": "@videospeach",
        "uploader_url": "https://www.youtube.com/@videospeach",
        "upload_date": "20170814",
        "duration": 2093,
        "view_count": 9832,
        "like_count": 292,
        "comment_count": 8,
        "tags": [
            "python",
            "pycon"
        ],
        "categories": [
            "Education"
        ],
        "description": "Выступление на конференции PYCON RUSSIA 2017",
        "thumbnail": "https://i.ytimg.com/vi_webp/Mhj8vqVUEhU/maxresdefault.webp",
        "age_limit": 0,
        "is_live": false,
        "was_live": false,
        "availability": "public",
        "webpage_url": "https://www.youtube.com/watch?v=Mhj8vqVUEhU",
        "original_url": "https://www.youtube.com/watch?v=Mhj8vqVUEhU"
    },
    {
        "index": 11,
        "title": "«Elegant Solutions for Everyday Python Problems» Nina Zakharenko, Venmo",
        "url": "https://www.youtube.com/watch?v=ZfKs-GDQyGs",
        "video_id": "ZfKs-GDQyGs",
        "uploader": "Видео с мероприятий {speach!",
        "uploader_id": "@videospeach",
        "uploader_url": "https://www.youtube.com/@videospeach",
        "upload_date": "20170814",
        "duration": 2620,
        "view_count": 1514,
        "like_count": 24,
        "comment_count": null,
        "tags": [
            "python",
            "pycon"
        ],
        "categories": [
            "Education"
        ],
        "description": "Выступление на конференции PYCON RUSSIA 2017",
        "thumbnail": "https://i.ytimg.com/vi_webp/ZfKs-GDQyGs/maxresdefault.webp",
        "age_limit": 0,
        "is_live": false,
        "was_live": false,
        "availability": "public",
        "webpage_url": "https://www.youtube.com/watch?v=ZfKs-GDQyGs",
        "original_url": "https://www.youtube.com/watch?v=ZfKs-GDQyGs"
    },
    {
        "index": 12,
        "title": "«Тотальный контроль производительности» Михаил Юматов, ЦИАН",
        "url": "https://www.youtube.com/watch?v=-J5UTQObcGM",
        "video_id": "-J5UTQObcGM",
        "uploader": "Видео с мероприятий {speach!",
        "uploader_id": "@videospeach",
        "uploader_url": "https://www.youtube.com/@videospeach",
        "upload_date": "20170814",
        "duration": 1472,
        "view_count": 1314,
        "like_count": 28,
        "comment_count": 4,
        "tags": [
            "python",
            "pycon"
        ],
        "categories": [
            "Education"
        ],
        "description": "Выступление на конференции PYCON RUSSIA 2017",
        "thumbnail": "https://i.ytimg.com/vi_webp/-J5UTQObcGM/maxresdefault.webp",
        "age_limit": 0,
        "is_live": false,
        "was_live": false,
        "availability": "public",
        "webpage_url": "https://www.youtube.com/watch?v=-J5UTQObcGM",
        "original_url": "https://www.youtube.com/watch?v=-J5UTQObcGM"
    },
    {
        "index": 13,
        "title": "Lightning Talks на PYCON RUSSIA 2017",
        "url": "https://www.youtube.com/watch?v=11vbB6vOWTE",
        "video_id": "11vbB6vOWTE",
        "uploader": "Видео с мероприятий {speach!",
        "uploader_id": "@videospeach",
        "uploader_url": "https://www.youtube.com/@videospeach",
        "upload_date": "20170814",
        "duration": 2819,
        "view_count": 530,
        "like_count": 8,
        "comment_count": 1,
        "tags": [
            "python",
            "pycon"
        ],
        "categories": [
            "Education"
        ],
        "description": "",
        "thumbnail": "https://i.ytimg.com/vi_webp/11vbB6vOWTE/maxresdefault.webp",
        "age_limit": 0,
        "is_live": false,
        "was_live": false,
        "availability": "public",
        "webpage_url": "https://www.youtube.com/watch?v=11vbB6vOWTE",
        "original_url": "https://www.youtube.com/watch?v=11vbB6vOWTE"
    },
    {
        "index": 14,
        "title": "«Gradual Typing of Production Applications» Łukasz Langa, Facebook",
        "url": "https://www.youtube.com/watch?v=Mn4AOttRmpI",
        "video_id": "Mn4AOttRmpI",
        "uploader": "Видео с мероприятий {speach!",
        "uploader_id": "@videospeach",
        "uploader_url": "https://www.youtube.com/@videospeach",
        "upload_date": "20170814",
        "duration": 3686,
        "view_count": 866,
        "like_count": 16,
        "comment_count": null,
        "tags": [
            "python",
            "pycon"
        ],
        "categories": [
            "Education"
        ],
        "description": "Выступление на конференции PYCON RUSSIA 2017",
        "thumbnail": "https://i.ytimg.com/vi_webp/Mn4AOttRmpI/maxresdefault.webp",
        "age_limit": 0,
        "is_live": false,
        "was_live": false,
        "availability": "public",
        "webpage_url": "https://www.youtube.com/watch?v=Mn4AOttRmpI",
        "original_url": "https://www.youtube.com/watch?v=Mn4AOttRmpI"
    },
    {
        "index": 15,
        "title": "«Gensim — тематическое моделирование для людей» Иван Меньших, Лев Константиновский",
        "url": "https://www.youtube.com/watch?v=TuJ_7OIxQWY",
        "video_id": "TuJ_7OIxQWY",
        "uploader": "Видео с мероприятий {speach!",
        "uploader_id": "@videospeach",
        "uploader_url": "https://www.youtube.com/@videospeach",
        "upload_date": "20170814",
        "duration": 1981,
        "view_count": 2238,
        "like_count": 59,
        "comment_count": 1,
        "tags": [
            "python",
            "pycon"
        ],
        "categories": [
            "Education"
        ],
        "description": "Выступление на конференции PYCON RUSSIA 2017",
        "thumbnail": "https://i.ytimg.com/vi_webp/TuJ_7OIxQWY/maxresdefault.webp",
        "age_limit": 0,
        "is_live": false,
        "was_live": false,
        "availability": "public",
        "webpage_url": "https://www.youtube.com/watch?v=TuJ_7OIxQWY",
        "original_url": "https://www.youtube.com/watch?v=TuJ_7OIxQWY"
    },
    {
        "index": 16,
        "title": "«Write once run anywhere — почём опиум для народа?» Игорь Новиков, Scalr",
        "url": "https://www.youtube.com/watch?v=fegxQcv3b-g",
        "video_id": "fegxQcv3b-g",
        "uploader": "Видео с мероприятий {speach!",
        "uploader_id": "@videospeach",
        "uploader_url": "https://www.youtube.com/@videospeach",
        "upload_date": "20170814",
        "duration": 1624,
        "view_count": 2471,
        "like_count": 40,
        "comment_count": 4,
        "tags": [
            "python",
            "pycon"
        ],
        "categories": [
            "Education"
        ],
        "description": "Выступление на PYCON RUSSIA 2017",
        "thumbnail": "https://i.ytimg.com/vi_webp/fegxQcv3b-g/maxresdefault.webp",
        "age_limit": 0,
        "is_live": false,
        "was_live": false,
        "availability": "public",
        "webpage_url": "https://www.youtube.com/watch?v=fegxQcv3b-g",
        "original_url": "https://www.youtube.com/watch?v=fegxQcv3b-g"
    },
    {
        "index": 17,
        "title": "«How I Learned to Stop Worrying and Love the BFG» Надежда Миргородская, Яндекс",
        "url": "https://www.youtube.com/watch?v=GLUBIUk_AXU",
        "video_id": "GLUBIUk_AXU",
        "uploader": "Видео с мероприятий {speach!",
        "uploader_id": "@videospeach",
        "uploader_url": "https://www.youtube.com/@videospeach",
        "upload_date": "20170814",
        "duration": 2060,
        "view_count": 1137,
        "like_count": 24,
        "comment_count": 1,
        "tags": [
            "python",
            "pycon"
        ],
        "categories": [
            "Education"
        ],
        "description": "Выступление на конференции PyCon Russia 2017",
        "thumbnail": "https://i.ytimg.com/vi_webp/GLUBIUk_AXU/maxresdefault.webp",
        "age_limit": 0,
        "is_live": false,
        "was_live": false,
        "availability": "public",
        "webpage_url": "https://www.youtube.com/watch?v=GLUBIUk_AXU",
        "original_url": "https://www.youtube.com/watch?v=GLUBIUk_AXU"
    },
    {
        "index": 18,
        "title": "«Про аналитику и серебряные пули» Александр Подсобляев, Rambler&Co",
        "url": "https://www.youtube.com/watch?v=KzwhWPLzmyM",
        "video_id": "KzwhWPLzmyM",
        "uploader": "Видео с мероприятий {speach!",
        "uploader_id": "@videospeach",
        "uploader_url": "https://www.youtube.com/@videospeach",
        "upload_date": "20170814",
        "duration": 2027,
        "view_count": 452,
        "like_count": 1,
        "comment_count": null,
        "tags": [
            "python",
            "pycon"
        ],
        "categories": [
            "Education"
        ],
        "description": "Выступление на конференции PYCON RUSSIA 2017",
        "thumbnail": "https://i.ytimg.com/vi_webp/KzwhWPLzmyM/maxresdefault.webp",
        "age_limit": 0,
        "is_live": false,
        "was_live": false,
        "availability": "public",
        "webpage_url": "https://www.youtube.com/watch?v=KzwhWPLzmyM",
        "original_url": "https://www.youtube.com/watch?v=KzwhWPLzmyM"
    },
    {
        "index": 19,
        "title": "«Ещё один Поиск Яндекса» Александр Кошелев, Яндекс",
        "url": "https://www.youtube.com/watch?v=UYrICNW4VYc",
        "video_id": "UYrICNW4VYc",
        "uploader": "Видео с мероприятий {speach!",
        "uploader_id": "@videospeach",
        "uploader_url": "https://www.youtube.com/@videospeach",
        "upload_date": "20170814",
        "duration": 1780,
        "view_count": 876,
        "like_count": 11,
        "comment_count": null,
        "tags": [
            "python",
            "pycon"
        ],
        "categories": [
            "Education"
        ],
        "description": "Выступление на конференции PYCON RUSSIA 2017",
        "thumbnail": "https://i.ytimg.com/vi_webp/UYrICNW4VYc/maxresdefault.webp",
        "age_limit": 0,
        "is_live": false,
        "was_live": false,
        "availability": "public",
        "webpage_url": "https://www.youtube.com/watch?v=UYrICNW4VYc",
        "original_url": "https://www.youtube.com/watch?v=UYrICNW4VYc"
    },
    {
        "index": 20,
        "title": "«Как написать свой debugger» Артём Малышев",
        "url": "https://www.youtube.com/watch?v=x7-RCv3jjqA",
        "video_id": "x7-RCv3jjqA",
        "uploader": "Видео с мероприятий {speach!",
        "uploader_id": "@videospeach",
        "uploader_url": "https://www.youtube.com/@videospeach",
        "upload_date": "20170809",
        "duration": 1920,
        "view_count": 821,
        "like_count": 18,
        "comment_count": null,
        "tags": [
            "python",
            "pucon"
        ],
        "categories": [
            "Education"
        ],
        "description": "Выступление на конференции PYCON RUSSIA 2017",
        "thumbnail": "https://i.ytimg.com/vi_webp/x7-RCv3jjqA/maxresdefault.webp",
        "age_limit": 0,
        "is_live": false,
        "was_live": false,
        "availability": "public",
        "webpage_url": "https://www.youtube.com/watch?v=x7-RCv3jjqA",
        "original_url": "https://www.youtube.com/watch?v=x7-RCv3jjqA"
    },
    {
        "index": 21,
        "title": "«Scrapy internals» Александр Сибиряков, Scrapinghub",
        "url": "https://www.youtube.com/watch?v=6hiXhNaWTTk",
        "video_id": "6hiXhNaWTTk",
        "uploader": "Видео с мероприятий {speach!",
        "uploader_id": "@videospeach",
        "uploader_url": "https://www.youtube.com/@videospeach",
        "upload_date": "20170814",
        "duration": 1769,
        "view_count": 2284,
        "like_count": 48,
        "comment_count": 2,
        "tags": [
            "python",
            "pycon"
        ],
        "categories": [
            "Education"
        ],
        "description": "Выступление на конференции PYCON RUSSIA 2017",
        "thumbnail": "https://i.ytimg.com/vi_webp/6hiXhNaWTTk/maxresdefault.webp",
        "age_limit": 0,
        "is_live": false,
        "was_live": false,
        "availability": "public",
        "webpage_url": "https://www.youtube.com/watch?v=6hiXhNaWTTk",
        "original_url": "https://www.youtube.com/watch?v=6hiXhNaWTTk"
    },
    {
        "index": 22,
        "title": "«Gevent — быть или не быть?» Александр Мокров, Positive Technologies",
        "url": "https://www.youtube.com/watch?v=yeUuRicgVCc",
        "video_id": "yeUuRicgVCc",
        "uploader": "Видео с мероприятий {speach!",
        "uploader_id": "@videospeach",
        "uploader_url": "https://www.youtube.com/@videospeach",
        "upload_date": "20170814",
        "duration": 2353,
        "view_count": 2252,
        "like_count": 35,
        "comment_count": 3,
        "tags": [
            "python",
            "pycon"
        ],
        "categories": [
            "Education"
        ],
        "description": "Выступление на конференции PYCON RUSSIA 2017",
        "thumbnail": "https://i.ytimg.com/vi_webp/yeUuRicgVCc/maxresdefault.webp",
        "age_limit": 0,
        "is_live": false,
        "was_live": false,
        "availability": "public",
        "webpage_url": "https://www.youtube.com/watch?v=yeUuRicgVCc",
        "original_url": "https://www.youtube.com/watch?v=yeUuRicgVCc"
    },
    {
        "index": 23,
        "title": "«Amazing AppEngine» Александр Хаёров, Ingram Micro",
        "url": "https://www.youtube.com/watch?v=8RZgIcEpSHA",
        "video_id": "8RZgIcEpSHA",
        "uploader": "Видео с мероприятий {speach!",
        "uploader_id": "@videospeach",
        "uploader_url": "https://www.youtube.com/@videospeach",
        "upload_date": "20170814",
        "duration": 1665,
        "view_count": 333,
        "like_count": 9,
        "comment_count": null,
        "tags": [
            "python",
            "pycon"
        ],
        "categories": [
            "Education"
        ],
        "description": "Выступление на конференции PYCON RUSSIA 2017",
        "thumbnail": "https://i.ytimg.com/vi_webp/8RZgIcEpSHA/maxresdefault.webp",
        "age_limit": 0,
        "is_live": false,
        "was_live": false,
        "availability": "public",
        "webpage_url": "https://www.youtube.com/watch?v=8RZgIcEpSHA",
        "original_url": "https://www.youtube.com/watch?v=8RZgIcEpSHA"
    },
    {
        "index": 24,
        "title": "«Отладка в Python 3.6: Быстрее, Выше, Сильнее» Елизавета Шашкова, JetBrains",
        "url": "https://www.youtube.com/watch?v=jK3D77b-DXk",
        "video_id": "jK3D77b-DXk",
        "uploader": "Видео с мероприятий {speach!",
        "uploader_id": "@videospeach",
        "uploader_url": "https://www.youtube.com/@videospeach",
        "upload_date": "20170814",
        "duration": 2295,
        "view_count": 4823,
        "like_count": 122,
        "comment_count": 3,
        "tags": [
            "python",
            "pycon"
        ],
        "categories": [
            "Education"
        ],
        "description": "Выступление на конференции PYCON RUSSIA 2017",
        "thumbnail": "https://i.ytimg.com/vi_webp/jK3D77b-DXk/maxresdefault.webp",
        "age_limit": 0,
        "is_live": false,
        "was_live": false,
        "availability": "public",
        "webpage_url": "https://www.youtube.com/watch?v=jK3D77b-DXk",
        "original_url": "https://www.youtube.com/watch?v=jK3D77b-DXk"
    }
]